<mxfile modified="2023-08-09T09:00:17.616Z" host="app.diagrams.net" agent="Mozilla/5.0 (Windows NT 10.0; Win64; x64) AppleWebKit/537.36 (KHTML, like Gecko) Chrome/115.0.0.0 Safari/537.36" etag="ptfFpauDGGGeMJM48lb-" version="21.6.7" type="github">
  <diagram id="Ht1M8jgEwFfnCIfOTk4-" name="Page-1">
    <mxGraphModel dx="3081" dy="2857" grid="1" gridSize="10" guides="1" tooltips="1" connect="1" arrows="1" fold="1" page="1" pageScale="1" pageWidth="1169" pageHeight="827" math="0" shadow="0">
      <root>
        <mxCell id="0" />
        <mxCell id="1" parent="0" />
        <object label="Kukuh Wikartomo - 2023" id="UAhBtCyf0KFtZmruoCBA-2">
          <mxCell style="text;html=1;strokeColor=none;fillColor=none;align=center;verticalAlign=middle;whiteSpace=wrap;rounded=0;" vertex="1" parent="1">
            <mxGeometry x="400.5" y="-1550" width="299" height="30" as="geometry" />
          </mxCell>
        </object>
        <mxCell id="F-A-o6JERDJgOEbKMBuy-97" value="" style="shape=step;perimeter=stepPerimeter;whiteSpace=wrap;html=1;fixedSize=1;fillColor=#FFE6CC;strokeWidth=3;strokeColor=#000000;fillStyle=hatch;gradientColor=#FFFFFF;gradientDirection=north;perimeterSpacing=0;shadow=1;" parent="1" vertex="1">
          <mxGeometry x="1120" y="-1640" width="380" height="750" as="geometry" />
        </mxCell>
        <mxCell id="F-A-o6JERDJgOEbKMBuy-44" value="" style="shape=step;perimeter=stepPerimeter;whiteSpace=wrap;html=1;fixedSize=1;fillColor=#CCFFFF;strokeWidth=3;strokeColor=#000000;fillStyle=hatch;gradientColor=#FFFFFF;gradientDirection=north;shadow=1;" parent="1" vertex="1">
          <mxGeometry x="370" y="-1640" width="490" height="750" as="geometry" />
        </mxCell>
        <mxCell id="F-A-o6JERDJgOEbKMBuy-35" value="" style="shape=step;perimeter=stepPerimeter;whiteSpace=wrap;html=1;fixedSize=1;fillColor=#CCCCFF;strokeWidth=2;gradientColor=#FFFFFF;fillStyle=solid;gradientDirection=north;" parent="1" vertex="1">
          <mxGeometry x="-270" y="-1640" width="340" height="750" as="geometry" />
        </mxCell>
        <mxCell id="F-A-o6JERDJgOEbKMBuy-28" value="" style="edgeStyle=orthogonalEdgeStyle;rounded=0;orthogonalLoop=1;jettySize=auto;html=1;" parent="1" source="F-A-o6JERDJgOEbKMBuy-2" target="F-A-o6JERDJgOEbKMBuy-27" edge="1">
          <mxGeometry relative="1" as="geometry" />
        </mxCell>
        <mxCell id="F-A-o6JERDJgOEbKMBuy-2" value="&lt;b&gt;&lt;font style=&quot;font-size: 14px;&quot;&gt;NMS&lt;/font&gt;&lt;/b&gt;" style="fillColor=none;strokeColor=#000000;verticalAlign=top;fontStyle=0;fontColor=#5A6C86;whiteSpace=wrap;html=1;fillStyle=hatch;gradientColor=none;" parent="1" vertex="1">
          <mxGeometry x="-230" y="-1493" width="249" height="190" as="geometry" />
        </mxCell>
        <object label="&lt;table&gt;&lt;tbody&gt;&lt;tr&gt;&lt;td&gt;&lt;br&gt;&lt;/td&gt;&lt;td&gt;&lt;br&gt;&lt;/td&gt;&lt;/tr&gt;&lt;/tbody&gt;&lt;/table&gt;" id="F-A-o6JERDJgOEbKMBuy-3">
          <mxCell style="sketch=0;outlineConnect=0;fontColor=#232F3E;gradientColor=none;fillColor=#232F3D;strokeColor=none;dashed=0;verticalLabelPosition=bottom;verticalAlign=top;align=center;html=1;fontSize=12;fontStyle=0;aspect=fixed;pointerEvents=1;shape=mxgraph.aws4.servers;" parent="1" vertex="1">
            <mxGeometry x="-219" y="-1443" width="60" height="60" as="geometry" />
          </mxCell>
        </object>
        <mxCell id="F-A-o6JERDJgOEbKMBuy-10" value="NMS-1" style="text;html=1;strokeColor=none;fillColor=none;align=center;verticalAlign=middle;whiteSpace=wrap;rounded=0;" parent="1" vertex="1">
          <mxGeometry x="-224" y="-1383" width="70" height="30" as="geometry" />
        </mxCell>
        <object label="&lt;table&gt;&lt;tbody&gt;&lt;tr&gt;&lt;td&gt;&lt;br&gt;&lt;/td&gt;&lt;td&gt;&lt;br&gt;&lt;/td&gt;&lt;/tr&gt;&lt;/tbody&gt;&lt;/table&gt;" id="F-A-o6JERDJgOEbKMBuy-11">
          <mxCell style="sketch=0;outlineConnect=0;fontColor=#232F3E;gradientColor=none;fillColor=#232F3D;strokeColor=none;dashed=0;verticalLabelPosition=bottom;verticalAlign=top;align=center;html=1;fontSize=12;fontStyle=0;aspect=fixed;pointerEvents=1;shape=mxgraph.aws4.servers;" parent="1" vertex="1">
            <mxGeometry x="-140" y="-1443" width="60" height="60" as="geometry" />
          </mxCell>
        </object>
        <mxCell id="F-A-o6JERDJgOEbKMBuy-12" value="NMS-2" style="text;html=1;strokeColor=none;fillColor=none;align=center;verticalAlign=middle;whiteSpace=wrap;rounded=0;" parent="1" vertex="1">
          <mxGeometry x="-145" y="-1383" width="70" height="30" as="geometry" />
        </mxCell>
        <object label="&lt;table&gt;&lt;tbody&gt;&lt;tr&gt;&lt;td&gt;&lt;br&gt;&lt;/td&gt;&lt;td&gt;&lt;br&gt;&lt;/td&gt;&lt;/tr&gt;&lt;/tbody&gt;&lt;/table&gt;" id="F-A-o6JERDJgOEbKMBuy-13">
          <mxCell style="sketch=0;outlineConnect=0;fontColor=#232F3E;gradientColor=none;fillColor=#232F3D;strokeColor=none;dashed=0;verticalLabelPosition=bottom;verticalAlign=top;align=center;html=1;fontSize=12;fontStyle=0;aspect=fixed;pointerEvents=1;shape=mxgraph.aws4.servers;" parent="1" vertex="1">
            <mxGeometry x="-60" y="-1443" width="60" height="60" as="geometry" />
          </mxCell>
        </object>
        <mxCell id="F-A-o6JERDJgOEbKMBuy-14" value="NMS-3" style="text;html=1;strokeColor=none;fillColor=none;align=center;verticalAlign=middle;whiteSpace=wrap;rounded=0;" parent="1" vertex="1">
          <mxGeometry x="-65" y="-1383" width="70" height="30" as="geometry" />
        </mxCell>
        <mxCell id="F-A-o6JERDJgOEbKMBuy-36" value="" style="shape=step;perimeter=stepPerimeter;whiteSpace=wrap;html=1;fixedSize=1;fillColor=#CCE5FF;strokeWidth=3;strokeColor=#000000;fillStyle=hatch;gradientColor=#FFFFFF;gradientDirection=north;shadow=1;" parent="1" vertex="1">
          <mxGeometry x="50" y="-1640" width="340" height="750" as="geometry" />
        </mxCell>
        <mxCell id="F-A-o6JERDJgOEbKMBuy-41" style="edgeStyle=orthogonalEdgeStyle;rounded=0;orthogonalLoop=1;jettySize=auto;html=1;" parent="1" source="F-A-o6JERDJgOEbKMBuy-27" target="F-A-o6JERDJgOEbKMBuy-38" edge="1">
          <mxGeometry relative="1" as="geometry" />
        </mxCell>
        <mxCell id="F-A-o6JERDJgOEbKMBuy-27" value="&lt;b&gt;&lt;font style=&quot;font-size: 14px;&quot;&gt;Exported Data&lt;/font&gt;&lt;/b&gt;" style="fillColor=none;strokeColor=#000000;verticalAlign=top;fontStyle=0;fontColor=#5A6C86;whiteSpace=wrap;html=1;fillStyle=hatch;gradientColor=none;movable=1;resizable=1;rotatable=1;deletable=1;editable=1;locked=0;connectable=1;" parent="1" vertex="1">
          <mxGeometry x="-230" y="-1240" width="249" height="133" as="geometry" />
        </mxCell>
        <mxCell id="F-A-o6JERDJgOEbKMBuy-17" value="" style="sketch=0;outlineConnect=0;fontColor=#232F3E;gradientColor=none;fillColor=#232F3D;strokeColor=none;dashed=0;verticalLabelPosition=bottom;verticalAlign=top;align=center;html=1;fontSize=12;fontStyle=0;aspect=fixed;pointerEvents=1;shape=mxgraph.aws4.document;" parent="1" vertex="1">
          <mxGeometry x="-194.9" y="-1187" width="36.54" height="50" as="geometry" />
        </mxCell>
        <mxCell id="F-A-o6JERDJgOEbKMBuy-19" value="" style="sketch=0;outlineConnect=0;fontColor=#232F3E;gradientColor=none;fillColor=#232F3D;strokeColor=none;dashed=0;verticalLabelPosition=bottom;verticalAlign=top;align=center;html=1;fontSize=12;fontStyle=0;aspect=fixed;pointerEvents=1;shape=mxgraph.aws4.document;" parent="1" vertex="1">
          <mxGeometry x="-120.90000000000003" y="-1187" width="36.54" height="50" as="geometry" />
        </mxCell>
        <mxCell id="F-A-o6JERDJgOEbKMBuy-20" value="" style="sketch=0;outlineConnect=0;fontColor=#232F3E;gradientColor=none;fillColor=#232F3D;strokeColor=none;dashed=0;verticalLabelPosition=bottom;verticalAlign=top;align=center;html=1;fontSize=12;fontStyle=0;aspect=fixed;pointerEvents=1;shape=mxgraph.aws4.document;" parent="1" vertex="1">
          <mxGeometry x="-52.63000000000004" y="-1187" width="36.54" height="50" as="geometry" />
        </mxCell>
        <mxCell id="F-A-o6JERDJgOEbKMBuy-43" style="edgeStyle=orthogonalEdgeStyle;rounded=0;orthogonalLoop=1;jettySize=auto;html=1;" parent="1" source="F-A-o6JERDJgOEbKMBuy-31" target="F-A-o6JERDJgOEbKMBuy-38" edge="1">
          <mxGeometry relative="1" as="geometry" />
        </mxCell>
        <mxCell id="F-A-o6JERDJgOEbKMBuy-31" value="&lt;font style=&quot;font-size: 14px;&quot;&gt;&lt;b&gt;Published Reports&lt;/b&gt;&lt;/font&gt;" style="fillColor=none;strokeColor=#000000;verticalAlign=top;fontStyle=0;fontColor=#5A6C86;whiteSpace=wrap;html=1;fillStyle=hatch;" parent="1" vertex="1">
          <mxGeometry x="-227.13" y="-1040" width="249" height="120" as="geometry" />
        </mxCell>
        <mxCell id="F-A-o6JERDJgOEbKMBuy-32" value="" style="sketch=0;outlineConnect=0;fontColor=#232F3E;gradientColor=none;fillColor=#232F3D;strokeColor=none;dashed=0;verticalLabelPosition=bottom;verticalAlign=top;align=center;html=1;fontSize=12;fontStyle=0;aspect=fixed;pointerEvents=1;shape=mxgraph.aws4.documents;" parent="1" vertex="1">
          <mxGeometry x="-131.74" y="-996.5" width="43.49" height="53" as="geometry" />
        </mxCell>
        <mxCell id="F-A-o6JERDJgOEbKMBuy-34" value="&lt;h1&gt;Data Collection&lt;/h1&gt;&lt;div&gt;Data collection refers to data collection from NMS data via scheduling and previous reports that have been created&lt;/div&gt;" style="text;html=1;strokeColor=none;fillColor=none;spacing=5;spacingTop=-20;whiteSpace=wrap;overflow=hidden;rounded=0;" parent="1" vertex="1">
          <mxGeometry x="-230" y="-1640" width="260" height="120" as="geometry" />
        </mxCell>
        <mxCell id="F-A-o6JERDJgOEbKMBuy-37" value="&lt;h1&gt;&lt;span style=&quot;background-color: initial;&quot;&gt;ETL&lt;/span&gt;&lt;/h1&gt;&lt;div&gt;Extract Transform Load process to prepare and/or convert the data necessary to be put in the data lake&lt;/div&gt;" style="text;html=1;strokeColor=none;fillColor=none;spacing=5;spacingTop=-20;whiteSpace=wrap;overflow=hidden;rounded=0;" parent="1" vertex="1">
          <mxGeometry x="80" y="-1640" width="270" height="120" as="geometry" />
        </mxCell>
        <mxCell id="F-A-o6JERDJgOEbKMBuy-55" style="edgeStyle=orthogonalEdgeStyle;rounded=0;orthogonalLoop=1;jettySize=auto;html=1;entryX=0.25;entryY=0;entryDx=0;entryDy=0;" parent="1" source="F-A-o6JERDJgOEbKMBuy-38" target="F-A-o6JERDJgOEbKMBuy-45" edge="1">
          <mxGeometry relative="1" as="geometry" />
        </mxCell>
        <mxCell id="F-A-o6JERDJgOEbKMBuy-38" value="" style="sketch=0;outlineConnect=0;fontColor=#232F3E;gradientColor=none;fillColor=#232F3D;strokeColor=none;dashed=0;verticalLabelPosition=bottom;verticalAlign=top;align=center;html=1;fontSize=12;fontStyle=0;aspect=fixed;pointerEvents=1;shape=mxgraph.aws4.gear;" parent="1" vertex="1">
          <mxGeometry x="181" y="-1304" width="74" height="74" as="geometry" />
        </mxCell>
        <mxCell id="F-A-o6JERDJgOEbKMBuy-39" value="ETL Engine" style="text;html=1;strokeColor=none;fillColor=none;align=center;verticalAlign=middle;whiteSpace=wrap;rounded=0;" parent="1" vertex="1">
          <mxGeometry x="179" y="-1340" width="80" height="30" as="geometry" />
        </mxCell>
        <mxCell id="F-A-o6JERDJgOEbKMBuy-89" style="edgeStyle=orthogonalEdgeStyle;rounded=0;orthogonalLoop=1;jettySize=auto;html=1;entryX=0.403;entryY=1.017;entryDx=0;entryDy=0;entryPerimeter=0;" parent="1" source="F-A-o6JERDJgOEbKMBuy-45" target="F-A-o6JERDJgOEbKMBuy-65" edge="1">
          <mxGeometry relative="1" as="geometry" />
        </mxCell>
        <mxCell id="F-A-o6JERDJgOEbKMBuy-45" value="" style="shape=document;whiteSpace=wrap;html=1;boundedLbl=1;strokeColor=none;gradientColor=#99FFFF;fillColor=default;" parent="1" vertex="1">
          <mxGeometry x="430" y="-1080" width="380" height="180" as="geometry" />
        </mxCell>
        <mxCell id="F-A-o6JERDJgOEbKMBuy-47" value="" style="sketch=0;outlineConnect=0;fontColor=#232F3E;gradientColor=none;fillColor=#232F3D;strokeColor=none;dashed=0;verticalLabelPosition=bottom;verticalAlign=top;align=center;html=1;fontSize=12;fontStyle=0;aspect=fixed;pointerEvents=1;shape=mxgraph.aws4.document;" parent="1" vertex="1">
          <mxGeometry x="471.72999999999996" y="-1015" width="36.54" height="50" as="geometry" />
        </mxCell>
        <mxCell id="F-A-o6JERDJgOEbKMBuy-48" value="" style="sketch=0;outlineConnect=0;fontColor=#232F3E;gradientColor=none;fillColor=#232F3D;strokeColor=none;dashed=0;verticalLabelPosition=bottom;verticalAlign=top;align=center;html=1;fontSize=12;fontStyle=0;aspect=fixed;pointerEvents=1;shape=mxgraph.aws4.document;" parent="1" vertex="1">
          <mxGeometry x="531.73" y="-1015" width="36.54" height="50" as="geometry" />
        </mxCell>
        <mxCell id="F-A-o6JERDJgOEbKMBuy-49" value="" style="sketch=0;outlineConnect=0;fontColor=#232F3E;gradientColor=none;fillColor=#232F3D;strokeColor=none;dashed=0;verticalLabelPosition=bottom;verticalAlign=top;align=center;html=1;fontSize=12;fontStyle=0;aspect=fixed;pointerEvents=1;shape=mxgraph.aws4.document;" parent="1" vertex="1">
          <mxGeometry x="591.73" y="-1015" width="36.54" height="50" as="geometry" />
        </mxCell>
        <mxCell id="F-A-o6JERDJgOEbKMBuy-51" value="" style="sketch=0;outlineConnect=0;fontColor=#232F3E;gradientColor=none;fillColor=#232F3D;strokeColor=none;dashed=0;verticalLabelPosition=bottom;verticalAlign=top;align=center;html=1;fontSize=12;fontStyle=0;aspect=fixed;pointerEvents=1;shape=mxgraph.aws4.document;" parent="1" vertex="1">
          <mxGeometry x="741.73" y="-1016.18" width="36.54" height="50" as="geometry" />
        </mxCell>
        <mxCell id="F-A-o6JERDJgOEbKMBuy-54" value="&lt;font style=&quot;font-size: 14px;&quot;&gt;&lt;b&gt;Object Storage&lt;/b&gt;&lt;/font&gt;" style="text;html=1;strokeColor=none;fillColor=none;align=center;verticalAlign=middle;whiteSpace=wrap;rounded=0;" parent="1" vertex="1">
          <mxGeometry x="569.07" y="-1070" width="120" height="30" as="geometry" />
        </mxCell>
        <mxCell id="F-A-o6JERDJgOEbKMBuy-56" value="&lt;h1&gt;Data Lake&lt;/h1&gt;&lt;div&gt;Data collection refers to data collection from NMS data via scheduling and previous reports that have been created&lt;/div&gt;" style="text;html=1;strokeColor=none;fillColor=none;spacing=5;spacingTop=-20;whiteSpace=wrap;overflow=hidden;rounded=0;" parent="1" vertex="1">
          <mxGeometry x="395" y="-1640" width="415" height="120" as="geometry" />
        </mxCell>
        <mxCell id="F-A-o6JERDJgOEbKMBuy-76" value="" style="shape=step;perimeter=stepPerimeter;whiteSpace=wrap;html=1;fixedSize=1;fillColor=#CCFFCC;strokeWidth=3;strokeColor=#000000;fillStyle=hatch;gradientColor=#FFFFFF;gradientDirection=north;shadow=1;" parent="1" vertex="1">
          <mxGeometry x="840" y="-1640" width="300" height="750" as="geometry" />
        </mxCell>
        <mxCell id="F-A-o6JERDJgOEbKMBuy-58" value="" style="endArrow=none;dashed=1;html=1;rounded=0;" parent="1" edge="1">
          <mxGeometry width="50" height="50" relative="1" as="geometry">
            <mxPoint x="410" y="-1106.5" as="sourcePoint" />
            <mxPoint x="840" y="-1107" as="targetPoint" />
          </mxGeometry>
        </mxCell>
        <mxCell id="F-A-o6JERDJgOEbKMBuy-59" value="Storage Layer" style="text;html=1;strokeColor=none;fillColor=none;align=center;verticalAlign=middle;whiteSpace=wrap;rounded=0;" parent="1" vertex="1">
          <mxGeometry x="395" y="-1130" width="115" height="30" as="geometry" />
        </mxCell>
        <mxCell id="F-A-o6JERDJgOEbKMBuy-62" value="" style="endArrow=none;dashed=1;html=1;rounded=0;" parent="1" edge="1">
          <mxGeometry width="50" height="50" relative="1" as="geometry">
            <mxPoint x="410" y="-1316.5" as="sourcePoint" />
            <mxPoint x="840" y="-1317" as="targetPoint" />
          </mxGeometry>
        </mxCell>
        <mxCell id="F-A-o6JERDJgOEbKMBuy-63" value="Metadata Layer" style="text;html=1;strokeColor=none;fillColor=none;align=center;verticalAlign=middle;whiteSpace=wrap;rounded=0;" parent="1" vertex="1">
          <mxGeometry x="395" y="-1340" width="115" height="30" as="geometry" />
        </mxCell>
        <mxCell id="F-A-o6JERDJgOEbKMBuy-90" style="edgeStyle=orthogonalEdgeStyle;rounded=0;orthogonalLoop=1;jettySize=auto;html=1;entryX=0.524;entryY=0;entryDx=0;entryDy=0;entryPerimeter=0;" parent="1" source="F-A-o6JERDJgOEbKMBuy-65" target="F-A-o6JERDJgOEbKMBuy-45" edge="1">
          <mxGeometry relative="1" as="geometry" />
        </mxCell>
        <mxCell id="F-A-o6JERDJgOEbKMBuy-65" value="" style="html=1;verticalLabelPosition=bottom;align=center;labelBackgroundColor=#ffffff;verticalAlign=top;strokeWidth=2;strokeColor=#000000;shadow=0;dashed=0;shape=mxgraph.ios7.icons.data;fillColor=none;" parent="1" vertex="1">
          <mxGeometry x="585" y="-1270" width="88.27" height="110" as="geometry" />
        </mxCell>
        <mxCell id="F-A-o6JERDJgOEbKMBuy-66" value="Metadata Catalog DB" style="text;html=1;strokeColor=none;fillColor=none;align=center;verticalAlign=middle;whiteSpace=wrap;rounded=0;" parent="1" vertex="1">
          <mxGeometry x="669.14" y="-1240" width="141.73" height="30" as="geometry" />
        </mxCell>
        <mxCell id="F-A-o6JERDJgOEbKMBuy-79" style="edgeStyle=orthogonalEdgeStyle;rounded=0;orthogonalLoop=1;jettySize=auto;html=1;" parent="1" source="F-A-o6JERDJgOEbKMBuy-71" target="F-A-o6JERDJgOEbKMBuy-65" edge="1">
          <mxGeometry relative="1" as="geometry">
            <mxPoint x="629" y="-1360" as="sourcePoint" />
            <Array as="points" />
          </mxGeometry>
        </mxCell>
        <mxCell id="F-A-o6JERDJgOEbKMBuy-82" style="edgeStyle=orthogonalEdgeStyle;rounded=0;orthogonalLoop=1;jettySize=auto;html=1;" parent="1" source="F-A-o6JERDJgOEbKMBuy-71" target="F-A-o6JERDJgOEbKMBuy-80" edge="1">
          <mxGeometry relative="1" as="geometry" />
        </mxCell>
        <mxCell id="F-A-o6JERDJgOEbKMBuy-113" style="edgeStyle=orthogonalEdgeStyle;rounded=0;orthogonalLoop=1;jettySize=auto;html=1;" parent="1" source="F-A-o6JERDJgOEbKMBuy-71" target="F-A-o6JERDJgOEbKMBuy-99" edge="1">
          <mxGeometry relative="1" as="geometry">
            <Array as="points">
              <mxPoint x="820" y="-1432" />
              <mxPoint x="820" y="-1432" />
            </Array>
          </mxGeometry>
        </mxCell>
        <mxCell id="F-A-o6JERDJgOEbKMBuy-71" value="" style="sketch=0;outlineConnect=0;fontColor=#232F3E;gradientColor=none;fillColor=#000000;strokeColor=none;dashed=0;verticalLabelPosition=bottom;verticalAlign=top;align=center;html=1;fontSize=12;fontStyle=0;aspect=fixed;pointerEvents=1;shape=mxgraph.aws4.servers;strokeWidth=1;" parent="1" vertex="1">
          <mxGeometry x="585" y="-1457.07" width="88.14" height="88.14" as="geometry" />
        </mxCell>
        <mxCell id="F-A-o6JERDJgOEbKMBuy-72" value="" style="endArrow=none;dashed=1;html=1;rounded=0;" parent="1" edge="1">
          <mxGeometry width="50" height="50" relative="1" as="geometry">
            <mxPoint x="405" y="-1486.5" as="sourcePoint" />
            <mxPoint x="835" y="-1487" as="targetPoint" />
          </mxGeometry>
        </mxCell>
        <mxCell id="F-A-o6JERDJgOEbKMBuy-73" value="Query / Processing Layer" style="text;html=1;strokeColor=none;fillColor=none;align=center;verticalAlign=middle;whiteSpace=wrap;rounded=0;" parent="1" vertex="1">
          <mxGeometry x="390" y="-1510" width="170" height="30" as="geometry" />
        </mxCell>
        <mxCell id="F-A-o6JERDJgOEbKMBuy-74" value="Distributed SQL query engine" style="text;html=1;strokeColor=none;fillColor=none;align=center;verticalAlign=middle;whiteSpace=wrap;rounded=0;" parent="1" vertex="1">
          <mxGeometry x="548.64" y="-1480" width="161" height="30" as="geometry" />
        </mxCell>
        <mxCell id="F-A-o6JERDJgOEbKMBuy-77" value="&lt;h1&gt;Data Warehouse&lt;/h1&gt;&lt;div&gt;Data collection refers to data collection from NMS data via scheduling and previous reports that have been created&lt;/div&gt;" style="text;html=1;strokeColor=none;fillColor=none;spacing=5;spacingTop=-20;whiteSpace=wrap;overflow=hidden;rounded=0;" parent="1" vertex="1">
          <mxGeometry x="860" y="-1640" width="240" height="120" as="geometry" />
        </mxCell>
        <mxCell id="F-A-o6JERDJgOEbKMBuy-87" value="Published Reports" style="fillColor=none;strokeColor=#5A6C86;dashed=1;verticalAlign=top;fontStyle=0;fontColor=#5A6C86;whiteSpace=wrap;html=1;" parent="1" vertex="1">
          <mxGeometry x="450" y="-1040" width="200" height="80" as="geometry" />
        </mxCell>
        <mxCell id="F-A-o6JERDJgOEbKMBuy-80" value="" style="html=1;verticalLabelPosition=bottom;align=center;labelBackgroundColor=#ffffff;verticalAlign=top;strokeWidth=2;strokeColor=#000000;shadow=0;dashed=0;shape=mxgraph.ios7.icons.data;fillColor=none;" parent="1" vertex="1">
          <mxGeometry x="925" y="-1285" width="110" height="140" as="geometry" />
        </mxCell>
        <mxCell id="F-A-o6JERDJgOEbKMBuy-92" style="edgeStyle=orthogonalEdgeStyle;rounded=0;orthogonalLoop=1;jettySize=auto;html=1;entryX=0.496;entryY=1.02;entryDx=0;entryDy=0;entryPerimeter=0;" parent="1" source="F-A-o6JERDJgOEbKMBuy-91" target="F-A-o6JERDJgOEbKMBuy-80" edge="1">
          <mxGeometry relative="1" as="geometry" />
        </mxCell>
        <mxCell id="F-A-o6JERDJgOEbKMBuy-91" value="NMS Data" style="fillColor=none;strokeColor=#5A6C86;dashed=1;verticalAlign=top;fontStyle=0;fontColor=#5A6C86;whiteSpace=wrap;html=1;" parent="1" vertex="1">
          <mxGeometry x="660" y="-1040" width="140" height="80" as="geometry" />
        </mxCell>
        <mxCell id="F-A-o6JERDJgOEbKMBuy-93" value="" style="sketch=0;outlineConnect=0;fontColor=#232F3E;gradientColor=none;fillColor=#232F3D;strokeColor=none;dashed=0;verticalLabelPosition=bottom;verticalAlign=top;align=center;html=1;fontSize=12;fontStyle=0;aspect=fixed;pointerEvents=1;shape=mxgraph.aws4.document;" parent="1" vertex="1">
          <mxGeometry x="690" y="-1016.18" width="36.54" height="50" as="geometry" />
        </mxCell>
        <mxCell id="F-A-o6JERDJgOEbKMBuy-94" value="Live Database" style="text;html=1;strokeColor=none;fillColor=none;align=center;verticalAlign=middle;whiteSpace=wrap;rounded=0;" parent="1" vertex="1">
          <mxGeometry x="1035" y="-1240" width="90" height="30" as="geometry" />
        </mxCell>
        <mxCell id="F-A-o6JERDJgOEbKMBuy-96" style="edgeStyle=orthogonalEdgeStyle;rounded=0;orthogonalLoop=1;jettySize=auto;html=1;" parent="1" edge="1">
          <mxGeometry relative="1" as="geometry">
            <mxPoint x="619.84" y="-1270" as="sourcePoint" />
            <mxPoint x="619.84" y="-1370" as="targetPoint" />
            <Array as="points" />
          </mxGeometry>
        </mxCell>
        <mxCell id="F-A-o6JERDJgOEbKMBuy-98" value="&lt;h1&gt;BI / Dashboard, AdHoc Query&lt;/h1&gt;&lt;div&gt;Data Processing for reports, dashboard and adhoc query&lt;/div&gt;" style="text;html=1;strokeColor=none;fillColor=none;spacing=5;spacingTop=-20;whiteSpace=wrap;overflow=hidden;rounded=0;" parent="1" vertex="1">
          <mxGeometry x="1125" y="-1640" width="350" height="120" as="geometry" />
        </mxCell>
        <mxCell id="F-A-o6JERDJgOEbKMBuy-99" value="" style="sketch=0;pointerEvents=1;shadow=0;dashed=0;html=1;strokeColor=none;fillColor=#434445;aspect=fixed;labelPosition=center;verticalLabelPosition=bottom;verticalAlign=top;align=center;outlineConnect=0;shape=mxgraph.vvd.nsx_dashboard;" parent="1" vertex="1">
          <mxGeometry x="1267.78" y="-1471" width="83.87" height="78" as="geometry" />
        </mxCell>
        <mxCell id="F-A-o6JERDJgOEbKMBuy-114" style="edgeStyle=orthogonalEdgeStyle;rounded=0;orthogonalLoop=1;jettySize=auto;html=1;" parent="1" target="F-A-o6JERDJgOEbKMBuy-101" edge="1">
          <mxGeometry relative="1" as="geometry">
            <mxPoint x="1230" y="-1430" as="sourcePoint" />
            <Array as="points">
              <mxPoint x="1230" y="-1259" />
            </Array>
          </mxGeometry>
        </mxCell>
        <mxCell id="F-A-o6JERDJgOEbKMBuy-101" value="" style="shape=image;html=1;verticalAlign=top;verticalLabelPosition=bottom;labelBackgroundColor=#ffffff;imageAspect=0;aspect=fixed;image=https://cdn0.iconfinder.com/data/icons/thin-line-icons-for-seo-and-development-1/64/Programming_Development_analysis-128.png" parent="1" vertex="1">
          <mxGeometry x="1263.21" y="-1306" width="93" height="93" as="geometry" />
        </mxCell>
        <mxCell id="F-A-o6JERDJgOEbKMBuy-115" style="edgeStyle=orthogonalEdgeStyle;rounded=0;orthogonalLoop=1;jettySize=auto;html=1;" parent="1" target="F-A-o6JERDJgOEbKMBuy-102" edge="1">
          <mxGeometry relative="1" as="geometry">
            <mxPoint x="1180" y="-1430" as="sourcePoint" />
            <Array as="points">
              <mxPoint x="1180" y="-1102" />
            </Array>
          </mxGeometry>
        </mxCell>
        <mxCell id="F-A-o6JERDJgOEbKMBuy-102" value="" style="sketch=0;outlineConnect=0;fontColor=#232F3E;gradientColor=none;fillColor=#000000;strokeColor=none;dashed=0;verticalLabelPosition=bottom;verticalAlign=top;align=center;html=1;fontSize=12;fontStyle=0;aspect=fixed;pointerEvents=1;shape=mxgraph.aws4.redshift_query_editor_v20_light;" parent="1" vertex="1">
          <mxGeometry x="1278.78" y="-1141" width="78" height="78" as="geometry" />
        </mxCell>
        <mxCell id="F-A-o6JERDJgOEbKMBuy-103" value="Dashboard" style="text;html=1;strokeColor=none;fillColor=none;align=center;verticalAlign=middle;whiteSpace=wrap;rounded=0;" parent="1" vertex="1">
          <mxGeometry x="1280" y="-1383" width="60" height="30" as="geometry" />
        </mxCell>
        <mxCell id="F-A-o6JERDJgOEbKMBuy-104" value="Reports" style="text;html=1;strokeColor=none;fillColor=none;align=center;verticalAlign=middle;whiteSpace=wrap;rounded=0;" parent="1" vertex="1">
          <mxGeometry x="1280" y="-1210" width="60" height="30" as="geometry" />
        </mxCell>
        <mxCell id="F-A-o6JERDJgOEbKMBuy-105" value="AdHoc Query" style="text;html=1;strokeColor=none;fillColor=none;align=center;verticalAlign=middle;whiteSpace=wrap;rounded=0;" parent="1" vertex="1">
          <mxGeometry x="1280" y="-1060" width="90" height="30" as="geometry" />
        </mxCell>
        <mxCell id="UAhBtCyf0KFtZmruoCBA-1" value="Text" style="text;html=1;strokeColor=none;fillColor=none;align=center;verticalAlign=middle;whiteSpace=wrap;rounded=0;" vertex="1" parent="1">
          <mxGeometry x="270" y="-1210" width="60" height="30" as="geometry" />
        </mxCell>
      </root>
    </mxGraphModel>
  </diagram>
</mxfile>
